sqerzo/__init__.py
sqerzo/__sqerzo__.py
sqerzo/config.py
sqerzo/exceptions.py
sqerzo/cache/__init__.py
sqerzo/cache/memory.py
sqerzo/graph/__init__.py
sqerzo/graph/helpers.py
sqerzo/graph/interfaces.py
sqerzo/graph/model.py
sqerzo/graph/query.py
sqerzo/graph/transaction.py
sqerzo/graph/cypher/__init__.py
sqerzo/graph/cypher/interfaces.py
sqerzo/graph/cypher/lang.py
sqerzo/graph/cypher/neo4j.py
sqerzo/graph/cypher/redisgraph.py
sqerzo/graph/cypher/transaction.py
sqerzo/graph/gremlin/__init__.py
sqerzo/graph/gremlin/gremlin.py
sqerzo-0.1.3.post2.dist-info/LICENSE
sqerzo-0.1.3.post2.dist-info/METADATA
sqerzo-0.1.3.post2.dist-info/WHEEL
sqerzo-0.1.3.post2.dist-info/top_level.txt
sqerzo-0.1.3.post2.dist-info/zip-safe
sqerzo-0.1.3.post2.dist-info/RECORD
