Metadata-Version: 2.1
Name: sqerzo
Version: 0.1.3.post2
Summary: Tiny ORM for graph databases
Home-page: https://github.com/BBVA/sqerzo
License: License :: OSI Approved :: Apache Software License
Platform: UNKNOWN
Classifier: License :: OSI Approved :: Apache Software License
Classifier: Programming Language :: Python :: 3.8
Requires-Python: >=3.8
Requires-Dist: neo4j
Requires-Dist: redisgraph
